[{"id": 2, "book_name": "In Cold Blood", "author": "Truman Capote", "type": "non-fiction", "page_numbers": "343"}, {"id": 3, "book_name": "The Curious Incident of the Dog in the Night-Time", "author": "Mark Haddon", "type": "detective", "page_numbers": "274"}, {"id": 4, "book_name": "The Great Gatsby", "author": "F. Scott Fitzgerald", "type": "fiction", "page_numbers": "180"}, {"id": 5, "book_name": "Lolita", "author": "Vladimir Nabokov", "type": "fiction", "page_numbers": "857"}, {"id": 6, "book_name": " Things Fall Apart", "author": "Chinua Achebe", "type": "fiction", "page_numbers": "465"}, {"id": 7, "book_name": "Hello World", "author": "Long", "type": "Programming Book", "page_numbers": 200}, {"id": 9, "book_name": "Hello World", "author": "Long", "type": "Code", "page_numbers": 500}, {"id": 8, "book_name": "Python Programming", "author": "Guido", "type": "Code", "page_numbers": 600}]